__init__.py
godspeak.py
godspeak-0.0.1.dist-info/LICENSE
godspeak-0.0.1.dist-info/METADATA
godspeak-0.0.1.dist-info/WHEEL
godspeak-0.0.1.dist-info/top_level.txt
godspeak-0.0.1.dist-info/RECORD
